mitesh_lib/__init__.py
mitesh_lib/tests.py
mitesh_lib/validate_palindrome.py
mitesh_palindrome_lib-0.1.5.dist-info/METADATA
mitesh_palindrome_lib-0.1.5.dist-info/WHEEL
mitesh_palindrome_lib-0.1.5.dist-info/top_level.txt
mitesh_palindrome_lib-0.1.5.dist-info/RECORD
